{
  "Firemaw": [],
  "Mograine": [],
  "Gehennas": [],
  "Whitemane": [
    {
      "player": {
        "currentQuests": [],
        "completedQuests": [],
        "level": 17,
        "experience": 14543,
        "uniquesGotten": [],
        "reputation": {
          "Southsea Pirates": 0,
          "Razormane Tribe": 0,
          "Pandaren": 0,
          "Grimtotem Tribe": 0,
          "Woodpaw Tribe": 0,
          "The Burning Legion": 0,
          "Darkspear Tribe": 4250,
          "Stormwind": 0,
          "Magram Clan": 0,
          "Gelkis Clan": 0,
          "Kolkar Clan": 0,
          "Orgrimmar": 4250,
          "Frostwolf Clan": 4250,
          "The Defiler's": 4250,
          "Thunder Bluff": 4600,
          "Undercity": 4250,
          "Ironforge": 0,
          "Dark Iron Clan": 0,
          "Wildhammer Clan": 0,
          "Winterfall Tribe": 0,
          "Gnomeregan": 0,
          "Darnassus": 0,
          "Bloodsail Buccaneers": 0,
          "Syndicate": 0,
          "Warsong Outriders": 4250,
          "Stormpike Guard": 0,
          "Silverwing Sentinels": 0,
          "The League of Arathor": 0,
          "Defias Brotherhood": 0,
          "Dalaran": 0,
          "Burning Blade Clan": 0,
          "Burning Legion": 0,
          "Shadow Council": 0,
          "Gordunni Ogres": 0,
          "Blackrock Clan": 0,
          "Dragonmaw Clan": 0,
          "Black Tooth Grin Clan": 0,
          "Gurubashi Tribe": 0,
          "Sandfury Tribe": 0,
          "Twilight's Hammer": 0,
          "Grimtotem Clan": 0,
          "Razorfen Tribe": 0,
          "Stonemaul Ogres": 4250,
          "Dustbelcher Ogres": 0,
          "Deadwind Ogres": 0,
          "Venture Co.": 0,
          "Southsea Freebooters": 0,
          "Atal'ai Tribe": 0,
          "Qiraji Empire": 0,
          "Scarlet Crusade": 0,
          "Vilebranch Tribe": 0,
          "Witherbark Tribe": 0,
          "Mossflayer Tribe": 0,
          "Frostmane Tribe": 0,
          "Bloodscalp Tribe": 0,
          "Skullsplitter Tribe": 0,
          "Shatterspear Tribe": 0,
          "Rot Hide Tribe": 0,
          "Scourge": 0,
          "Smolderthorn Tribe": 0,
          "Revantusk Tribe": 4250,
          "Blackpaw Tribe": 0,
          "Maraudine Clan": 0,
          "Mosshide Tribe": 0,
          "Deadwood Tribe": 0,
          "Bloodtooth Tribe": 0,
          "Bristleback Tribe": 0
        },
        "professionSkills": {},
        "learnedRecipes": {},
        "unspentTalentPoints": 1,
        "faction": "Thunder Bluff",
        "name": "Quana",
        "race": "Tauren",
        "spec": "Druid",
        "gender": "Female",
        "homeLocation": "Camp Narache",
        "abilities": {
          "Two Handed Mace Proficiency": 1,
          "Staff Proficiency": 1,
          "Leather Proficiency": 1,
          "One Handed Mace Proficiency": 1,
          "Off Hand Proficiency": 1,
          "Fist Weapon Proficiency": 1,
          "Dagger Proficiency": 1,
          "Idol Proficiency": 1,
          "Wrath": 0,
          "Rake": 0,
          "Regrowth": 0,
          "Verdant Heart": 0,
          "Mangle": 0,
          "Thrash": 0,
          "Thick Hide": 0,
          "Bear Form": 0,
          "Moonfire": 0,
          "Eclipse": 0,
          "Light of the Sun": 0,
          "Sunfire": 0,
          "Shooting Stars": 0,
          "Star Surge": 0,
          "Lunar Shrapnel": 0,
          "Cosmic Rapidity": 0,
          "Faerie Fire": 0,
          "Cyclone": 0
        },
        "currentActionSet": "Bear Form",
        "actionBars": {
          "Default": [
            "Wrath",
            "Moonfire",
            "Bear Form"
          ],
          "Bear Form": [
            "Leave Bear Form",
            "Wrath",
            "Moonfire"
          ]
        },
        "stats": {
          "stats": {
            "Stamina": 23,
            "Strength": 25,
            "Agility": 15,
            "Intellect": 17,
            "Spirit": 24,
            "Earth Mastery": 3,
            "Fire Mastery": 2,
            "Air Mastery": 3,
            "Water Mastery": 3,
            "Frost Mastery": 1,
            "Lightning Mastery": 1,
            "Arcane Mastery": 2,
            "Decay Mastery": 1,
            "Shadow Mastery": 1,
            "Order Mastery": 2
          }
        },
        "inventory": {
          "money": 1423,
          "items": [
            {
              "rarity": "Common",
              "name": "Hearthstone",
              "icon": "itemmiscrune01",
              "detailedType": "Rune",
              "type": "Miscellaneous",
              "ilvl": 1,
              "amount": 1,
              "maxStack": 1,
              "indestructible": true,
              "unique": true,
              "abilities": {
                "Hearthstone": 1
              }
            }
          ],
          "bags": [
            {
              "rarity": "Common",
              "name": "Old Moneybag",
              "icon": "itemmiscbag10",
              "type": "Bag",
              "source": "DirectDrop",
              "ilvl": 5,
              "lvl": 1,
              "amount": 1,
              "maxStack": 1,
              "unique": true,
              "price": 250,
              "bagSpace": 2,
              "droppedBy": [
                "Tharm"
              ]
            }
          ]
        },
        "mounts": [],
        "equipment": {
          "Main Hand": {
            "rarity": "Common",
            "name": "Bent Staff",
            "icon": "itemstaff08",
            "detailedType": "Staff",
            "type": "Two Handed",
            "ilvl": 2,
            "lvl": 1,
            "minDamage": 3,
            "maxDamage": 5,
            "amount": 1,
            "maxStack": 1,
            "price": 9,
            "speed": 2.9
          },
          "Legs": {
            "rarity": "Poor",
            "name": "Novice's Pants",
            "icon": "itempants01",
            "type": "Legs",
            "armorClass": "Cloth",
            "ilvl": 1,
            "lvl": 1,
            "armor": 2,
            "amount": 1,
            "maxStack": 1,
            "price": 1
          },
          "Chest": {
            "rarity": "Poor",
            "name": "Novice's Robe",
            "icon": "itemchestcloth13",
            "type": "Chest",
            "armorClass": "Cloth",
            "ilvl": 1,
            "lvl": 1,
            "armor": 3,
            "amount": 1,
            "maxStack": 1,
            "price": 1
          }
        },
        "worldBuffs": []
      },
      "hour": 7,
      "minute": 51,
      "second": 18,
      "currentSite": "The Dragonmurk",
      "ringOfLaw": "Hedrum the Creeper",
      "forlornCloister": "Ironspine",
      "openedChests": {},
      "fishingSpots": {},
      "fishingSpoils": {},
      "siteProgress": {},
      "commonsKilled": {},
      "raresKilled": {},
      "elitesKilled": {},
      "siteVisits": {
        "Camp Narache": 2,
        "Red Cloud Mesa": 7,
        "The Washed Hillside": 1,
        "Bloodhoof Village": 1,
        "The Rolling Plains": 1,
        "Field of Giants": 1,
        "Southern Gold Road": 0,
        "Shady Rest Inn": 1,
        "Lost Point": 1,
        "Bloodfen Burrow": 1,
        "The Den of Flame": 1,
        "The Dragonmurk": 4
      },
      "unlockedAreas": [],
      "vendorStock": {},
      "banks": {},
      "startDate": "2024-07-24T17:02:59.9048011+02:00",
      "lastLoaded": "2024-07-25T21:10:14.4190285+02:00",
      "lastPlayed": "2024-07-25T21:10:40.4477965+02:00",
      "timePlayed": "01:04:14.5603704"
    },
    {
      "player": {
        "currentQuests": [
          {
            "questID": 6561,
            "requiredLevel": 18,
            "questLevel": 27,
            "name": "Blackfathom Villainy",
            "description": "Strength has left me. Your help is needed!$B$BLong ago this site was a great temple of Elune. But misfortune led to ruin when the corruption of an Old God seeped up from beneath the earth and tainted the sacred Moon Well.$B$BAku'Mai, servant of the Old God, rose from the waters.$B$BThe Twilight's Hammer cultists have allied with the naga to occupy these grounds. The cultists, led by Kelris, sacrifice innocents to Aku'Mai for power.$B$BSlay Kelris and bring his head to Bashana in Thunder Bluff, $N, please.",
            "objective": "Bring the head of Twilight Lord Kelris to Bashana Runetotem in Thunder Bluff.",
            "completion": "Kelris has eluded the Argent Dawn for some time.$B$BFor some time they considered him dead or missing.$B$BBy ending his reign you have spared the lives of many innocent people, $N.$B$BEarthmother be praised! To sacrifice another to a servant of an Old God for personal gain is beyond disgusting!$B$BYou have done a great thing this day. Kelris was a creature of evil and sought to bring the world back to a time of chaos by worshipping such creatures as the Old Gods. Thank you, $N.",
            "siteStart": "Thunder Bluff",
            "siteEnd": "Thunder Bluff",
            "zone": "Blackfathom Deeps",
            "money": 6500,
            "experience": 3300,
            "races": [
              "Troll",
              "Tauren",
              "Forsaken",
              "Orc"
            ],
            "rewards": {
              "Gravestone Scepter": 1,
              "Arctic Buckler": 1
            },
            "reputationGain": {
              "Argent Dawn": 200,
              "Thunder Bluff": 500
            },
            "conditions": [
              {
                "type": "Item",
                "name": "Head of Kelris",
                "amount": 1
              }
            ]
          },
          {
            "questID": 6541,
            "requiredLevel": 17,
            "questLevel": 19,
            "name": "Report to Kadrak",
            "description": "Have you ever been to Ashenvale, to the north? The horde has recently set up an outpost on the Zoram Strand there, and we can always use some new recruits to help defend our new fronts.$B$BIf you think you are up to it, see Kadrak in the northern Barrens, at the watch tower. He is heading up the Ashenvale campaign and can give you further orders.",
            "objective": "Report to Kadrak at the watch tower in northern Barrens.",
            "completion": "Ashenvale is a divided land, but our most recent efforts have been very successful. We not only have an outpost at the Zoram Strand, but another just north of here called Splintertree.",
            "siteStart": "The Crossroads",
            "siteEnd": "The Mor'shan Rampart",
            "zone": "The Barrens",
            "experience": 145,
            "races": [
              "Troll",
              "Tauren",
              "Forsaken",
              "Orc"
            ],
            "conditions": []
          }
        ],
        "completedQuests": [
          4921,
          6548
        ],
        "level": 24,
        "experience": 28428,
        "uniquesGotten": [],
        "reputation": {
          "Southsea Pirates": 0,
          "Razormane Tribe": 0,
          "Pandaren": 0,
          "Grimtotem Tribe": 0,
          "Woodpaw Tribe": 0,
          "The Burning Legion": 0,
          "Darkspear Tribe": 4250,
          "Stormwind": 0,
          "Magram Clan": 0,
          "Gelkis Clan": 0,
          "Kolkar Clan": 0,
          "Orgrimmar": 4400,
          "Frostwolf Clan": 4250,
          "The Defiler's": 4250,
          "Thunder Bluff": 4850,
          "Undercity": 4250,
          "Ironforge": 0,
          "Dark Iron Clan": 0,
          "Wildhammer Clan": 0,
          "Winterfall Tribe": 0,
          "Gnomeregan": 0,
          "Darnassus": 0,
          "Bloodsail Buccaneers": 0,
          "Syndicate": 0,
          "Warsong Outriders": 4250,
          "Stormpike Guard": 0,
          "Silverwing Sentinels": 0,
          "The League of Arathor": 0,
          "Defias Brotherhood": 0,
          "Dalaran": 0,
          "Burning Blade Clan": 0,
          "Burning Legion": 0,
          "Shadow Council": 0,
          "Gordunni Ogres": 0,
          "Blackrock Clan": 0,
          "Dragonmaw Clan": 0,
          "Black Tooth Grin Clan": 0,
          "Gurubashi Tribe": 0,
          "Sandfury Tribe": 0,
          "Twilight's Hammer": 0,
          "Grimtotem Clan": 0,
          "Razorfen Tribe": 0,
          "Stonemaul Ogres": 4250,
          "Dustbelcher Ogres": 0,
          "Deadwind Ogres": 0,
          "Venture Co.": 0,
          "Southsea Freebooters": 0,
          "Atal'ai Tribe": 0,
          "Qiraji Empire": 0,
          "Scarlet Crusade": 0,
          "Vilebranch Tribe": 0,
          "Witherbark Tribe": 0,
          "Mossflayer Tribe": 0,
          "Frostmane Tribe": 0,
          "Bloodscalp Tribe": 0,
          "Skullsplitter Tribe": 0,
          "Shatterspear Tribe": 0,
          "Rot Hide Tribe": 0,
          "Scourge": 0,
          "Smolderthorn Tribe": 0,
          "Revantusk Tribe": 4250,
          "Blackpaw Tribe": 0,
          "Maraudine Clan": 0,
          "Mosshide Tribe": 0,
          "Deadwood Tribe": 0,
          "Bloodtooth Tribe": 0,
          "Bristleback Tribe": 0
        },
        "professionSkills": {
          "Enchanting": {
            "Item1": 1,
            "Item2": [
              "Apprentice"
            ]
          }
        },
        "learnedRecipes": {
          "Enchanting": [
            "Runed Copper Rod",
            "Enchant Bracer - Minor Deflect",
            "Enchant Bracer - Minor Health"
          ]
        },
        "unspentTalentPoints": 6,
        "faction": "Thunder Bluff",
        "name": "Hannaya",
        "race": "Tauren",
        "spec": "Warrior",
        "gender": "Female",
        "homeLocation": "Camp Narache",
        "abilities": {
          "Dual Wielding Proficiency": 0,
          "Two Handed Axe Proficiency": 0,
          "Two Handed Mace Proficiency": 0,
          "Two Handed Sword Proficiency": 0,
          "Polearm Proficiency": 0,
          "Shield Proficiency": 0,
          "Mail Proficiency": 0,
          "Plate Proficiency": 0,
          "One Handed Axe Proficiency": 0,
          "One Handed Mace Proficiency": 0,
          "One Handed Sword Proficiency": 0,
          "Fist Weapon Proficiency": 0,
          "Off Hand Proficiency": 0,
          "Heroic Strike": 0,
          "Battle Shout": 0,
          "Bloodthirst": 0,
          "Revenge": 0,
          "Charge": 0,
          "Deflection": 0,
          "Rend": 0,
          "Overpower": 0,
          "Thunder Clap": 0,
          "Cruelty": 0,
          "Bloodcraze": 0,
          "Demoralizing Shout": 0,
          "Slam": 0,
          "War Machine": 0,
          "Immense Strength": 0,
          "Whirlwind": 0,
          "Fresh Meat": 0,
          "Blind Rage": 0,
          "Execute": 0,
          "Enrage": 0,
          "Berserker Rage": 0
        },
        "currentActionSet": "Default",
        "actionBars": {
          "Default": [
            "Heroic Strike",
            "Thunder Clap",
            "Execute"
          ]
        },
        "stats": {
          "stats": {
            "Stamina": 24,
            "Strength": 28,
            "Agility": 15,
            "Intellect": 15,
            "Spirit": 22,
            "Earth Mastery": 3,
            "Fire Mastery": 2,
            "Air Mastery": 3,
            "Water Mastery": 3,
            "Frost Mastery": 1,
            "Lightning Mastery": 1,
            "Arcane Mastery": 2,
            "Decay Mastery": 1,
            "Shadow Mastery": 1,
            "Order Mastery": 2
          }
        },
        "inventory": {
          "money": 31036,
          "items": [
            {
              "rarity": "Common",
              "name": "Hearthstone",
              "icon": "itemmiscrune01",
              "detailedType": "Rune",
              "type": "Miscellaneous",
              "ilvl": 1,
              "amount": 1,
              "maxStack": 1,
              "indestructible": true,
              "unique": true,
              "abilities": {
                "Hearthstone": 1
              }
            },
            {
              "rarity": "Common",
              "name": "Ritual Salve",
              "icon": "itempotion01",
              "detailedType": "Potion",
              "type": "Miscellaneous",
              "source": "DirectDrop",
              "ilvl": 1,
              "amount": 1,
              "maxStack": 20,
              "droppedBy": [
                "Bristleback Shaman"
              ]
            },
            {
              "rarity": "Uncommon",
              "name": "Jade",
              "icon": "itemmiscgemstone01",
              "detailedType": "Gem",
              "type": "Trade Good",
              "source": "Quest",
              "ilvl": 35,
              "lvl": 1,
              "amount": 7,
              "maxStack": 20,
              "price": 700
            },
            {
              "rarity": "Uncommon",
              "name": "Citrine",
              "icon": "itemmiscgemopal02",
              "detailedType": "Gem",
              "type": "Trade Good",
              "source": "RareDrop",
              "ilvl": 40,
              "lvl": 1,
              "amount": 9,
              "maxStack": 20,
              "price": 800
            },
            {
              "rarity": "Uncommon",
              "name": "Arcane Crystal",
              "icon": "itemmiscgemtopaz01",
              "detailedType": "Gem",
              "type": "Trade Good",
              "ilvl": 60,
              "lvl": 1,
              "amount": 1,
              "maxStack": 20,
              "price": 2000
            },
            {
              "rarity": "Uncommon",
              "name": "Aquamarine",
              "icon": "itemmiscgemcrystal02",
              "detailedType": "Gem",
              "type": "Trade Good",
              "source": "RareDrop",
              "ilvl": 45,
              "lvl": 1,
              "amount": 6,
              "maxStack": 20,
              "price": 1000
            },
            {
              "rarity": "Uncommon",
              "name": "Azerothian Diamond",
              "icon": "itemmiscgemdiamond01",
              "detailedType": "Gem",
              "type": "Trade Good",
              "ilvl": 60,
              "lvl": 1,
              "amount": 2,
              "maxStack": 20,
              "price": 10000
            },
            {
              "rarity": "Uncommon",
              "name": "Schematic: Master Engineer's Goggles",
              "icon": "itemscroll06",
              "detailedType": "Scroll",
              "type": "Recipe",
              "source": "DirectDrop",
              "amount": 1,
              "maxStack": 1,
              "price": 5000,
              "droppedBy": [
                "Doomforge Arcanasmith"
              ]
            },
            {
              "rarity": "Common",
              "name": "Scroll of Intellect IV",
              "icon": "itemscroll01",
              "detailedType": "Scroll",
              "type": "Miscellaneous",
              "source": "RareDrop",
              "ilvl": 60,
              "amount": 1,
              "maxStack": 5,
              "abilities": {
                "Scroll of Intellect IV": 1
              },
              "price": 112
            },
            {
              "rarity": "Common",
              "name": "Runecloth",
              "icon": "itemfabricpurplefire01",
              "detailedType": "Cloth",
              "type": "Trade Good",
              "source": "RareDrop",
              "ilvl": 50,
              "lvl": 1,
              "amount": 3,
              "maxStack": 20,
              "price": 400
            },
            {
              "rarity": "Uncommon",
              "name": "Schematic: Master Engineer's Goggles",
              "icon": "itemscroll06",
              "detailedType": "Scroll",
              "type": "Recipe",
              "source": "DirectDrop",
              "amount": 1,
              "maxStack": 1,
              "price": 5000,
              "droppedBy": [
                "Doomforge Arcanasmith"
              ]
            },
            {
              "rarity": "Poor",
              "name": "Laminated Scale Bracers",
              "icon": "itembracer03",
              "type": "Wrists",
              "armorClass": "Mail",
              "source": "RareDrop",
              "ilvl": 58,
              "lvl": 53,
              "armor": 123,
              "amount": 1,
              "maxStack": 1,
              "price": 4404
            },
            {
              "rarity": "Rare",
              "name": "Shalehusk Boots",
              "icon": "itembootsplate01",
              "type": "Feet",
              "armorClass": "Plate",
              "source": "DirectDrop",
              "ilvl": 58,
              "lvl": 53,
              "armor": 417,
              "amount": 1,
              "maxStack": 1,
              "price": 13732,
              "stats": {
                "stats": {
                  "Stamina": 5
                }
              },
              "droppedBy": [
                "Panzor the Invincible"
              ]
            },
            {
              "rarity": "Uncommon",
              "name": "Impenetrable Breastplate of the Tiger",
              "icon": "itemchestplate01",
              "randomEnchantment": true,
              "type": "Chest",
              "armorClass": "Mail",
              "source": "RareDrop",
              "ilvl": 61,
              "lvl": 56,
              "armor": 327,
              "amount": 1,
              "maxStack": 1,
              "price": 26315,
              "stats": {
                "stats": {
                  "Agility": 17,
                  "Strength": 17
                }
              }
            }
          ],
          "bags": [
            {
              "rarity": "Common",
              "name": "Runecloth Bag",
              "icon": "itemmiscbag19",
              "type": "Bag",
              "source": "Profession",
              "ilvl": 52,
              "lvl": 1,
              "amount": 1,
              "maxStack": 1,
              "price": 5000,
              "bagSpace": 6
            }
          ]
        },
        "mounts": [],
        "equipment": {
          "Main Hand": {
            "rarity": "Rare",
            "name": "Ironpatch Blade",
            "icon": "itemsword26",
            "detailedType": "Sword",
            "type": "One Handed",
            "source": "RareDrop",
            "ilvl": 20,
            "lvl": 15,
            "minDamage": 24,
            "maxDamage": 46,
            "amount": 1,
            "maxStack": 1,
            "price": 1770,
            "speed": 2.6,
            "stats": {
              "stats": {
                "Strength": 4,
                "Stamina": 2
              }
            }
          },
          "Legs": {
            "rarity": "Poor",
            "name": "Brawler's Pants",
            "icon": "itempants02",
            "type": "Legs",
            "armorClass": "Cloth",
            "ilvl": 1,
            "lvl": 1,
            "armor": 2,
            "amount": 1,
            "maxStack": 1,
            "price": 1
          },
          "Chest": {
            "rarity": "Common",
            "name": "Brawler's Harness",
            "icon": "itemchestleather04",
            "type": "Chest",
            "ilvl": 1,
            "lvl": 1,
            "amount": 1,
            "maxStack": 1,
            "price": 1
          },
          "Back": {
            "rarity": "Common",
            "name": "Bloodspattered Cloak",
            "icon": "itemmisccape22",
            "type": "Back",
            "source": "RareDrop",
            "ilvl": 14,
            "lvl": 9,
            "armor": 12,
            "amount": 1,
            "maxStack": 1,
            "price": 105
          }
        },
        "worldBuffs": []
      },
      "hour": 9,
      "minute": 5,
      "second": 30,
      "currentSite": "Blackrock Mountain",
      "ringOfLaw": "Eviscerator",
      "forlornCloister": "Ironspine",
      "openedChests": {},
      "fishingSpots": {},
      "fishingSpoils": {},
      "siteProgress": {
        "Red Cloud Mesa": 2,
        "Brambleblade Ravine": 1,
        "Camp Aparaje": 2,
        "Mold Foundry": 2,
        "Summoners' Tomb": 2
      },
      "commonsKilled": {
        "Plainstrider": 1,
        "Mountain Cougar": 1,
        "Bristleback Shaman": 1,
        "Grimtotem Mercenary": 1,
        "Grimtotem Ruffian": 1,
        "Doomforge Arcanasmith": 2,
        "Cannibal Ghoul": 2
      },
      "raresKilled": {},
      "elitesKilled": {
        "Panzor the Invincible": 1,
        "The Seven": 1
      },
      "siteVisits": {
        "Camp Narache": 4,
        "Red Cloud Mesa": 2,
        "Brambleblade Ravine": 1,
        "The Washed Hillside": 1,
        "Bloodhoof Village": 2,
        "Stonebull Lake": 0,
        "Thunder Bluff": 5,
        "The Rolling Plains": 0,
        "Camp Taurajo": 1,
        "The Riverbed": 1,
        "Central Gold Road": 0,
        "The Crossroads": 2,
        "Honor's Stand": 2,
        "Camp Aparaje": 1,
        "Far Watch Post": 0,
        "Orgrimmar": 7,
        "Skull Rock": 1,
        "Blackrock Mountain": 5
      },
      "unlockedAreas": [
        "Summoners' Tomb",
        "The Iron Hall",
        "Molten Core"
      ],
      "vendorStock": {
        "Camp Narache:Kawnie Softbreeze": [
          {
            "item": "Refreshing Spring Water",
            "amount": 2,
            "maxAmount": 2,
            "restockSpeed": 40
          },
          {
            "item": "Rough Arrow",
            "amount": 2,
            "maxAmount": 2,
            "restockSpeed": 40
          },
          {
            "item": "Light Shot",
            "amount": 2,
            "maxAmount": 2,
            "restockSpeed": 40
          },
          {
            "item": "Small Throwing Knife",
            "amount": 2,
            "maxAmount": 2,
            "restockSpeed": 40
          },
          {
            "item": "Crude Throwing Axe",
            "amount": 2,
            "maxAmount": 2,
            "restockSpeed": 40
          },
          {
            "item": "Tough Hunk of Bread",
            "amount": 2,
            "maxAmount": 2,
            "restockSpeed": 40
          }
        ],
        "Camp Narache:Marjak Keenblade": [
          {
            "item": "Bastard Sword",
            "amount": 2,
            "maxAmount": 2,
            "restockSpeed": 40
          },
          {
            "item": "Club",
            "amount": 2,
            "maxAmount": 2,
            "restockSpeed": 40
          },
          {
            "item": "Shortsword",
            "amount": 2,
            "maxAmount": 2,
            "restockSpeed": 40
          },
          {
            "item": "Short Staff",
            "amount": 2,
            "maxAmount": 2,
            "restockSpeed": 40
          },
          {
            "item": "Hand Axe",
            "amount": 2,
            "maxAmount": 2,
            "restockSpeed": 40
          },
          {
            "item": "Dirk",
            "amount": 2,
            "maxAmount": 2,
            "restockSpeed": 40
          },
          {
            "item": "Broad Axe",
            "amount": 2,
            "maxAmount": 2,
            "restockSpeed": 40
          },
          {
            "item": "Large Club",
            "amount": 2,
            "maxAmount": 2,
            "restockSpeed": 40
          }
        ],
        "Orgrimmar:Sovik": [
          {
            "item": "Weak Flux",
            "amount": 2,
            "maxAmount": 2,
            "restockSpeed": 40
          },
          {
            "item": "Mining Pick",
            "amount": 2,
            "maxAmount": 2,
            "restockSpeed": 40
          },
          {
            "item": "Strong Flux",
            "amount": 2,
            "maxAmount": 2,
            "restockSpeed": 40
          },
          {
            "item": "Rough Blasting Powder",
            "amount": 2,
            "maxAmount": 2,
            "restockSpeed": 40
          },
          {
            "item": "Copper Tube",
            "amount": 2,
            "maxAmount": 2,
            "restockSpeed": 40
          },
          {
            "item": "Copper Modulator",
            "amount": 2,
            "maxAmount": 2,
            "restockSpeed": 40
          },
          {
            "item": "Coarse Blasting Powder",
            "amount": 2,
            "maxAmount": 2,
            "restockSpeed": 40
          },
          {
            "item": "Bronze Tube",
            "amount": 2,
            "maxAmount": 2,
            "restockSpeed": 40
          },
          {
            "item": "Bronze Framework",
            "amount": 2,
            "maxAmount": 2,
            "restockSpeed": 40
          },
          {
            "item": "Gyrochronatom",
            "amount": 2,
            "maxAmount": 2,
            "restockSpeed": 40
          },
          {
            "item": "Wooden Stock",
            "amount": 2,
            "maxAmount": 2,
            "restockSpeed": 40
          },
          {
            "item": "Heavy Stock",
            "amount": 2,
            "maxAmount": 2,
            "restockSpeed": 40
          },
          {
            "item": "Silver Contact",
            "amount": 2,
            "maxAmount": 2,
            "restockSpeed": 40
          },
          {
            "item": "Blacksmith Hammer",
            "amount": 2,
            "maxAmount": 2,
            "restockSpeed": 40
          },
          {
            "item": "Engineer's Ink",
            "amount": 2,
            "maxAmount": 2,
            "restockSpeed": 40
          },
          {
            "item": "Blank Parchment",
            "amount": 2,
            "maxAmount": 2,
            "restockSpeed": 40
          },
          {
            "item": "Schematic: Thorium Grenade",
            "amount": 2,
            "maxAmount": 2,
            "restockSpeed": 40
          },
          {
            "item": "Schematic: Thorium Widget",
            "amount": 2,
            "maxAmount": 2,
            "restockSpeed": 40
          },
          {
            "item": "Schematic: Red Firework",
            "amount": 2,
            "maxAmount": 2,
            "restockSpeed": 40
          }
        ],
        "Orgrimmar:Ollanus": [
          {
            "item": "Thick Cloth Vest",
            "amount": 2,
            "maxAmount": 2,
            "restockSpeed": 40
          },
          {
            "item": "Thick Cloth Pants",
            "amount": 2,
            "maxAmount": 2,
            "restockSpeed": 40
          },
          {
            "item": "Thick Cloth Shoes",
            "amount": 2,
            "maxAmount": 2,
            "restockSpeed": 40
          },
          {
            "item": "Thick Cloth Gloves",
            "amount": 2,
            "maxAmount": 2,
            "restockSpeed": 40
          },
          {
            "item": "Heavy Weave Armor",
            "amount": 2,
            "maxAmount": 2,
            "restockSpeed": 40
          },
          {
            "item": "Heavy Weave Pants",
            "amount": 2,
            "maxAmount": 2,
            "restockSpeed": 40
          },
          {
            "item": "Heavy Weave Gloves",
            "amount": 2,
            "maxAmount": 2,
            "restockSpeed": 40
          },
          {
            "item": "Heavy Weave Shoes",
            "amount": 2,
            "maxAmount": 2,
            "restockSpeed": 40
          },
          {
            "item": "Woven Vest",
            "amount": 2,
            "maxAmount": 2,
            "restockSpeed": 40
          },
          {
            "item": "Woven Pants",
            "amount": 2,
            "maxAmount": 2,
            "restockSpeed": 40
          },
          {
            "item": "Woven Boots",
            "amount": 2,
            "maxAmount": 2,
            "restockSpeed": 40
          },
          {
            "item": "Woven Gloves",
            "amount": 2,
            "maxAmount": 2,
            "restockSpeed": 40
          },
          {
            "item": "Common Gray Shirt",
            "amount": 2,
            "maxAmount": 2,
            "restockSpeed": 40
          },
          {
            "item": "Heavy Weave Belt",
            "amount": 2,
            "maxAmount": 2,
            "restockSpeed": 40
          },
          {
            "item": "Heavy Weave Bracers",
            "amount": 2,
            "maxAmount": 2,
            "restockSpeed": 40
          },
          {
            "item": "Thick Cloth Belt",
            "amount": 2,
            "maxAmount": 2,
            "restockSpeed": 40
          },
          {
            "item": "Thick Cloth Bracers",
            "amount": 2,
            "maxAmount": 2,
            "restockSpeed": 40
          },
          {
            "item": "Woven Belt",
            "amount": 2,
            "maxAmount": 2,
            "restockSpeed": 40
          },
          {
            "item": "Woven Bracers",
            "amount": 2,
            "maxAmount": 2,
            "restockSpeed": 40
          },
          {
            "item": "Common Brown Shirt",
            "amount": 2,
            "maxAmount": 2,
            "restockSpeed": 40
          },
          {
            "item": "Common White Shirt",
            "amount": 2,
            "maxAmount": 2,
            "restockSpeed": 40
          }
        ]
      },
      "banks": {
        "Thunder Bluff": {
          "items": [
            {
              "rarity": "Common",
              "name": "Crude Throwing Axe",
              "icon": "itemaxe19",
              "type": "Miscellaneous",
              "ilvl": 3,
              "minDamage": 1,
              "maxDamage": 3,
              "amount": 2,
              "maxStack": 200,
              "speed": 2.0
            }
          ],
          "bags": []
        },
        "Orgrimmar": {
          "items": [
            {
              "rarity": "Common",
              "name": "Battleworn Hammer",
              "icon": "itemhammer15",
              "detailedType": "Mace",
              "type": "Two Handed",
              "ilvl": 2,
              "lvl": 1,
              "minDamage": 3,
              "maxDamage": 5,
              "amount": 1,
              "maxStack": 1,
              "price": 9,
              "speed": 2.9
            }
          ],
          "bags": []
        }
      },
      "buyback": {
        "items": [],
        "bags": [],
        "ignoreSpaceChecks": true
      },
      "startDate": "2024-07-25T21:10:47.9718315+02:00",
      "lastLoaded": "2024-07-30T04:49:16.4058814+02:00",
      "lastPlayed": "2024-07-30T04:53:20.9431144+02:00",
      "timePlayed": "00:37:06.1647091",
      "lastVisitedTalents": 1
    }
  ]
}